model_ident/__init__.py
model_ident/apps.py
tests/__init__.py
tests/models.py
tests/test.py
django_model_ident-0.2.dist-info/LICENSE
django_model_ident-0.2.dist-info/METADATA
django_model_ident-0.2.dist-info/WHEEL
django_model_ident-0.2.dist-info/top_level.txt
django_model_ident-0.2.dist-info/RECORD
