Metadata-Version: 2.1
Name: django-model-ident
Version: 0.2
Summary: Django app to provide classes quick pk only lookups
Home-page: https://github.com/ckirby/django-model-ident
Author: Chaim Kirby
Author-email: chaim.kirby@gmail.com
License: UNKNOWN
Platform: UNKNOWN
Classifier: Development Status :: 4 - Beta
Classifier: Framework :: Django
Classifier: Intended Audience :: Developers
Classifier: License :: OSI Approved :: BSD License
Classifier: Natural Language :: English
Classifier: Programming Language :: Python :: 3.4
Classifier: Programming Language :: Python :: 3.5
Classifier: Programming Language :: Python :: 3.6
Classifier: Programming Language :: Python :: 3.7
